sampledit/__init__.py
sampledit-0.0.1.dist-info/LICENCE.txt
sampledit-0.0.1.dist-info/METADATA
sampledit-0.0.1.dist-info/WHEEL
sampledit-0.0.1.dist-info/top_level.txt
sampledit-0.0.1.dist-info/RECORD
