Metadata-Version: 2.1
Name: sampledit
Version: 0.0.1
Summary: dit document layout
Author: sneha dhole
License: UNKNOWN
Platform: UNKNOWN
License-File: LICENCE.txt
Requires-Dist: torch
Requires-Dist: pyyaml
Requires-Dist: torchvision
Requires-Dist: opencv-python
